<?xml version="1.0" encoding="UTF-8"?>
<!DOCTYPE mapper PUBLIC "-//mybatis.org//DTD Mapper 3.0//EN" "http://mybatis.org/dtd/mybatis-3-mapper.dtd">
<mapper namespace="com.ehais.school_weixin.mapper.WyBuildingMapper">
  <resultMap id="BaseResultMap" type="com.ehais.school_weixin.model.WyBuilding">
    <!--
      WARNING - @mbg.generated
      This element is automatically generated by MyBatis Generator, do not modify.
      This element was generated on Mon Dec 05 15:58:20 CST 2016.
    -->
    <id column="building_id" jdbcType="INTEGER" property="building_id" />
    <result column="building_code" jdbcType="VARCHAR" property="building_code" />
    <result column="building_name" jdbcType="VARCHAR" property="building_name" />
    <result column="building_unit_quantity" jdbcType="INTEGER" property="building_unit_quantity" />
    <result column="building_floor_quantity" jdbcType="INTEGER" property="building_floor_quantity" />
    <result column="building_house_quantity" jdbcType="INTEGER" property="building_house_quantity" />
    <result column="building_community_id" jdbcType="INTEGER" property="building_community_id" />
    <result column="building_house_type_id" jdbcType="INTEGER" property="building_house_type_id" />
  </resultMap>
  <resultMap extends="BaseResultMap" id="ResultMapWithBLOBs" type="com.ehais.school_weixin.model.WyBuilding">
    <!--
      WARNING - @mbg.generated
      This element is automatically generated by MyBatis Generator, do not modify.
      This element was generated on Mon Dec 05 15:58:20 CST 2016.
    -->
    <result column="building_remark" jdbcType="LONGVARCHAR" property="building_remark" />
  </resultMap>
  <sql id="Example_Where_Clause">
    <!--
      WARNING - @mbg.generated
      This element is automatically generated by MyBatis Generator, do not modify.
      This element was generated on Mon Dec 05 15:58:20 CST 2016.
    -->
    <where>
      <foreach collection="oredCriteria" item="criteria" separator="or">
        <if test="criteria.valid">
          <trim prefix="(" prefixOverrides="and" suffix=")">
            <foreach collection="criteria.criteria" item="criterion">
              <choose>
                <when test="criterion.noValue">
                  and ${criterion.condition}
                </when>
                <when test="criterion.singleValue">
                  and ${criterion.condition} #{criterion.value}
                </when>
                <when test="criterion.betweenValue">
                  and ${criterion.condition} #{criterion.value} and #{criterion.secondValue}
                </when>
                <when test="criterion.listValue">
                  and ${criterion.condition}
                  <foreach close=")" collection="criterion.value" item="listItem" open="(" separator=",">
                    #{listItem}
                  </foreach>
                </when>
              </choose>
            </foreach>
          </trim>
        </if>
      </foreach>
    </where>
  </sql>
  <sql id="Update_By_Example_Where_Clause">
    <!--
      WARNING - @mbg.generated
      This element is automatically generated by MyBatis Generator, do not modify.
      This element was generated on Mon Dec 05 15:58:20 CST 2016.
    -->
    <where>
      <foreach collection="example.oredCriteria" item="criteria" separator="or">
        <if test="criteria.valid">
          <trim prefix="(" prefixOverrides="and" suffix=")">
            <foreach collection="criteria.criteria" item="criterion">
              <choose>
                <when test="criterion.noValue">
                  and ${criterion.condition}
                </when>
                <when test="criterion.singleValue">
                  and ${criterion.condition} #{criterion.value}
                </when>
                <when test="criterion.betweenValue">
                  and ${criterion.condition} #{criterion.value} and #{criterion.secondValue}
                </when>
                <when test="criterion.listValue">
                  and ${criterion.condition}
                  <foreach close=")" collection="criterion.value" item="listItem" open="(" separator=",">
                    #{listItem}
                  </foreach>
                </when>
              </choose>
            </foreach>
          </trim>
        </if>
      </foreach>
    </where>
  </sql>
  <sql id="Base_Column_List">
    <!--
      WARNING - @mbg.generated
      This element is automatically generated by MyBatis Generator, do not modify.
      This element was generated on Mon Dec 05 15:58:20 CST 2016.
    -->
    building_id, building_code, building_name, building_unit_quantity, building_floor_quantity, 
    building_house_quantity, building_community_id, building_house_type_id
  </sql>
  <sql id="Blob_Column_List">
    <!--
      WARNING - @mbg.generated
      This element is automatically generated by MyBatis Generator, do not modify.
      This element was generated on Mon Dec 05 15:58:20 CST 2016.
    -->
    building_remark
  </sql>
  <select id="selectByExampleWithBLOBs" parameterType="com.ehais.school_weixin.model.WyBuildingExample" resultMap="ResultMapWithBLOBs">
    <!--
      WARNING - @mbg.generated
      This element is automatically generated by MyBatis Generator, do not modify.
      This element was generated on Mon Dec 05 15:58:20 CST 2016.
    -->
    select
    <if test="distinct">
      distinct
    </if>
    <include refid="Base_Column_List" />
    ,
    <include refid="Blob_Column_List" />
    from wy_building
    <if test="_parameter != null">
      <include refid="Example_Where_Clause" />
    </if>
    <if test="orderByClause != null">
      order by ${orderByClause}
    </if>
  </select>
  <select id="selectByExample" parameterType="com.ehais.school_weixin.model.WyBuildingExample" resultMap="BaseResultMap">
    <!--
      WARNING - @mbg.generated
      This element is automatically generated by MyBatis Generator, do not modify.
      This element was generated on Mon Dec 05 15:58:20 CST 2016.
    -->
    select
    <if test="distinct">
      distinct
    </if>
    <include refid="Base_Column_List" />
    from wy_building
    <if test="_parameter != null">
      <include refid="Example_Where_Clause" />
    </if>
    <if test="orderByClause != null">
      order by ${orderByClause}
    </if>
  </select>
  <select id="selectByPrimaryKey" parameterType="java.lang.Integer" resultMap="ResultMapWithBLOBs">
    <!--
      WARNING - @mbg.generated
      This element is automatically generated by MyBatis Generator, do not modify.
      This element was generated on Mon Dec 05 15:58:20 CST 2016.
    -->
    select 
    <include refid="Base_Column_List" />
    ,
    <include refid="Blob_Column_List" />
    from wy_building
    where building_id = #{building_id,jdbcType=INTEGER}
  </select>
  <delete id="deleteByPrimaryKey" parameterType="java.lang.Integer">
    <!--
      WARNING - @mbg.generated
      This element is automatically generated by MyBatis Generator, do not modify.
      This element was generated on Mon Dec 05 15:58:20 CST 2016.
    -->
    delete from wy_building
    where building_id = #{building_id,jdbcType=INTEGER}
  </delete>
  <delete id="deleteByExample" parameterType="com.ehais.school_weixin.model.WyBuildingExample">
    <!--
      WARNING - @mbg.generated
      This element is automatically generated by MyBatis Generator, do not modify.
      This element was generated on Mon Dec 05 15:58:20 CST 2016.
    -->
    delete from wy_building
    <if test="_parameter != null">
      <include refid="Example_Where_Clause" />
    </if>
  </delete>
  <insert id="insert" parameterType="com.ehais.school_weixin.model.WyBuilding">
    <!--
      WARNING - @mbg.generated
      This element is automatically generated by MyBatis Generator, do not modify.
      This element was generated on Mon Dec 05 15:58:20 CST 2016.
    -->
    insert into wy_building (building_id, building_code, building_name, 
      building_unit_quantity, building_floor_quantity, 
      building_house_quantity, building_community_id, 
      building_house_type_id, building_remark
      )
    values (#{building_id,jdbcType=INTEGER}, #{building_code,jdbcType=VARCHAR}, #{building_name,jdbcType=VARCHAR}, 
      #{building_unit_quantity,jdbcType=INTEGER}, #{building_floor_quantity,jdbcType=INTEGER}, 
      #{building_house_quantity,jdbcType=INTEGER}, #{building_community_id,jdbcType=INTEGER}, 
      #{building_house_type_id,jdbcType=INTEGER}, #{building_remark,jdbcType=LONGVARCHAR}
      )
  </insert>
  <insert id="insertSelective" parameterType="com.ehais.school_weixin.model.WyBuilding">
    <!--
      WARNING - @mbg.generated
      This element is automatically generated by MyBatis Generator, do not modify.
      This element was generated on Mon Dec 05 15:58:20 CST 2016.
    -->
    insert into wy_building
    <trim prefix="(" suffix=")" suffixOverrides=",">
      <if test="building_id != null">
        building_id,
      </if>
      <if test="building_code != null">
        building_code,
      </if>
      <if test="building_name != null">
        building_name,
      </if>
      <if test="building_unit_quantity != null">
        building_unit_quantity,
      </if>
      <if test="building_floor_quantity != null">
        building_floor_quantity,
      </if>
      <if test="building_house_quantity != null">
        building_house_quantity,
      </if>
      <if test="building_community_id != null">
        building_community_id,
      </if>
      <if test="building_house_type_id != null">
        building_house_type_id,
      </if>
      <if test="building_remark != null">
        building_remark,
      </if>
    </trim>
    <trim prefix="values (" suffix=")" suffixOverrides=",">
      <if test="building_id != null">
        #{building_id,jdbcType=INTEGER},
      </if>
      <if test="building_code != null">
        #{building_code,jdbcType=VARCHAR},
      </if>
      <if test="building_name != null">
        #{building_name,jdbcType=VARCHAR},
      </if>
      <if test="building_unit_quantity != null">
        #{building_unit_quantity,jdbcType=INTEGER},
      </if>
      <if test="building_floor_quantity != null">
        #{building_floor_quantity,jdbcType=INTEGER},
      </if>
      <if test="building_house_quantity != null">
        #{building_house_quantity,jdbcType=INTEGER},
      </if>
      <if test="building_community_id != null">
        #{building_community_id,jdbcType=INTEGER},
      </if>
      <if test="building_house_type_id != null">
        #{building_house_type_id,jdbcType=INTEGER},
      </if>
      <if test="building_remark != null">
        #{building_remark,jdbcType=LONGVARCHAR},
      </if>
    </trim>
  </insert>
  <select id="countByExample" parameterType="com.ehais.school_weixin.model.WyBuildingExample" resultType="java.lang.Long">
    <!--
      WARNING - @mbg.generated
      This element is automatically generated by MyBatis Generator, do not modify.
      This element was generated on Mon Dec 05 15:58:20 CST 2016.
    -->
    select count(*) from wy_building
    <if test="_parameter != null">
      <include refid="Example_Where_Clause" />
    </if>
  </select>
  <update id="updateByExampleSelective" parameterType="map">
    <!--
      WARNING - @mbg.generated
      This element is automatically generated by MyBatis Generator, do not modify.
      This element was generated on Mon Dec 05 15:58:20 CST 2016.
    -->
    update wy_building
    <set>
      <if test="record.building_id != null">
        building_id = #{record.building_id,jdbcType=INTEGER},
      </if>
      <if test="record.building_code != null">
        building_code = #{record.building_code,jdbcType=VARCHAR},
      </if>
      <if test="record.building_name != null">
        building_name = #{record.building_name,jdbcType=VARCHAR},
      </if>
      <if test="record.building_unit_quantity != null">
        building_unit_quantity = #{record.building_unit_quantity,jdbcType=INTEGER},
      </if>
      <if test="record.building_floor_quantity != null">
        building_floor_quantity = #{record.building_floor_quantity,jdbcType=INTEGER},
      </if>
      <if test="record.building_house_quantity != null">
        building_house_quantity = #{record.building_house_quantity,jdbcType=INTEGER},
      </if>
      <if test="record.building_community_id != null">
        building_community_id = #{record.building_community_id,jdbcType=INTEGER},
      </if>
      <if test="record.building_house_type_id != null">
        building_house_type_id = #{record.building_house_type_id,jdbcType=INTEGER},
      </if>
      <if test="record.building_remark != null">
        building_remark = #{record.building_remark,jdbcType=LONGVARCHAR},
      </if>
    </set>
    <if test="_parameter != null">
      <include refid="Update_By_Example_Where_Clause" />
    </if>
  </update>
  <update id="updateByExampleWithBLOBs" parameterType="map">
    <!--
      WARNING - @mbg.generated
      This element is automatically generated by MyBatis Generator, do not modify.
      This element was generated on Mon Dec 05 15:58:20 CST 2016.
    -->
    update wy_building
    set building_id = #{record.building_id,jdbcType=INTEGER},
      building_code = #{record.building_code,jdbcType=VARCHAR},
      building_name = #{record.building_name,jdbcType=VARCHAR},
      building_unit_quantity = #{record.building_unit_quantity,jdbcType=INTEGER},
      building_floor_quantity = #{record.building_floor_quantity,jdbcType=INTEGER},
      building_house_quantity = #{record.building_house_quantity,jdbcType=INTEGER},
      building_community_id = #{record.building_community_id,jdbcType=INTEGER},
      building_house_type_id = #{record.building_house_type_id,jdbcType=INTEGER},
      building_remark = #{record.building_remark,jdbcType=LONGVARCHAR}
    <if test="_parameter != null">
      <include refid="Update_By_Example_Where_Clause" />
    </if>
  </update>
  <update id="updateByExample" parameterType="map">
    <!--
      WARNING - @mbg.generated
      This element is automatically generated by MyBatis Generator, do not modify.
      This element was generated on Mon Dec 05 15:58:20 CST 2016.
    -->
    update wy_building
    set building_id = #{record.building_id,jdbcType=INTEGER},
      building_code = #{record.building_code,jdbcType=VARCHAR},
      building_name = #{record.building_name,jdbcType=VARCHAR},
      building_unit_quantity = #{record.building_unit_quantity,jdbcType=INTEGER},
      building_floor_quantity = #{record.building_floor_quantity,jdbcType=INTEGER},
      building_house_quantity = #{record.building_house_quantity,jdbcType=INTEGER},
      building_community_id = #{record.building_community_id,jdbcType=INTEGER},
      building_house_type_id = #{record.building_house_type_id,jdbcType=INTEGER}
    <if test="_parameter != null">
      <include refid="Update_By_Example_Where_Clause" />
    </if>
  </update>
  <update id="updateByPrimaryKeySelective" parameterType="com.ehais.school_weixin.model.WyBuilding">
    <!--
      WARNING - @mbg.generated
      This element is automatically generated by MyBatis Generator, do not modify.
      This element was generated on Mon Dec 05 15:58:20 CST 2016.
    -->
    update wy_building
    <set>
      <if test="building_code != null">
        building_code = #{building_code,jdbcType=VARCHAR},
      </if>
      <if test="building_name != null">
        building_name = #{building_name,jdbcType=VARCHAR},
      </if>
      <if test="building_unit_quantity != null">
        building_unit_quantity = #{building_unit_quantity,jdbcType=INTEGER},
      </if>
      <if test="building_floor_quantity != null">
        building_floor_quantity = #{building_floor_quantity,jdbcType=INTEGER},
      </if>
      <if test="building_house_quantity != null">
        building_house_quantity = #{building_house_quantity,jdbcType=INTEGER},
      </if>
      <if test="building_community_id != null">
        building_community_id = #{building_community_id,jdbcType=INTEGER},
      </if>
      <if test="building_house_type_id != null">
        building_house_type_id = #{building_house_type_id,jdbcType=INTEGER},
      </if>
      <if test="building_remark != null">
        building_remark = #{building_remark,jdbcType=LONGVARCHAR},
      </if>
    </set>
    where building_id = #{building_id,jdbcType=INTEGER}
  </update>
  <update id="updateByPrimaryKeyWithBLOBs" parameterType="com.ehais.school_weixin.model.WyBuilding">
    <!--
      WARNING - @mbg.generated
      This element is automatically generated by MyBatis Generator, do not modify.
      This element was generated on Mon Dec 05 15:58:20 CST 2016.
    -->
    update wy_building
    set building_code = #{building_code,jdbcType=VARCHAR},
      building_name = #{building_name,jdbcType=VARCHAR},
      building_unit_quantity = #{building_unit_quantity,jdbcType=INTEGER},
      building_floor_quantity = #{building_floor_quantity,jdbcType=INTEGER},
      building_house_quantity = #{building_house_quantity,jdbcType=INTEGER},
      building_community_id = #{building_community_id,jdbcType=INTEGER},
      building_house_type_id = #{building_house_type_id,jdbcType=INTEGER},
      building_remark = #{building_remark,jdbcType=LONGVARCHAR}
    where building_id = #{building_id,jdbcType=INTEGER}
  </update>
  <update id="updateByPrimaryKey" parameterType="com.ehais.school_weixin.model.WyBuilding">
    <!--
      WARNING - @mbg.generated
      This element is automatically generated by MyBatis Generator, do not modify.
      This element was generated on Mon Dec 05 15:58:20 CST 2016.
    -->
    update wy_building
    set building_code = #{building_code,jdbcType=VARCHAR},
      building_name = #{building_name,jdbcType=VARCHAR},
      building_unit_quantity = #{building_unit_quantity,jdbcType=INTEGER},
      building_floor_quantity = #{building_floor_quantity,jdbcType=INTEGER},
      building_house_quantity = #{building_house_quantity,jdbcType=INTEGER},
      building_community_id = #{building_community_id,jdbcType=INTEGER},
      building_house_type_id = #{building_house_type_id,jdbcType=INTEGER}
    where building_id = #{building_id,jdbcType=INTEGER}
  </update>
</mapper>